mcp_agent/__init__.py
mcp_agent/app.py
mcp_agent/config.py
mcp_agent/console.py
mcp_agent/context.py
mcp_agent/context_dependent.py
mcp_agent/event_progress.py
mcp_agent/mcp_server_registry.py
mcp_agent/progress_display.py
mcp_agent/agents/__init__.py
mcp_agent/agents/agent.py
mcp_agent/agents/base_agent.py
mcp_agent/agents/workflow/__init__.py
mcp_agent/agents/workflow/chain_agent.py
mcp_agent/agents/workflow/evaluator_optimizer.py
mcp_agent/agents/workflow/orchestrator_agent.py
mcp_agent/agents/workflow/orchestrator_models.py
mcp_agent/agents/workflow/orchestrator_prompts.py
mcp_agent/agents/workflow/parallel_agent.py
mcp_agent/agents/workflow/router_agent.py
mcp_agent/cli/__init__.py
mcp_agent/cli/__main__.py
mcp_agent/cli/main.py
mcp_agent/cli/terminal.py
mcp_agent/cli/commands/check_config.py
mcp_agent/cli/commands/go.py
mcp_agent/cli/commands/quickstart.py
mcp_agent/cli/commands/setup.py
mcp_agent/cli/commands/url_parser.py
mcp_agent/core/__init__.py
mcp_agent/core/agent_app.py
mcp_agent/core/agent_types.py
mcp_agent/core/direct_decorators.py
mcp_agent/core/direct_factory.py
mcp_agent/core/enhanced_prompt.py
mcp_agent/core/error_handling.py
mcp_agent/core/exceptions.py
mcp_agent/core/fastagent.py
mcp_agent/core/interactive_prompt.py
mcp_agent/core/mcp_content.py
mcp_agent/core/prompt.py
mcp_agent/core/redis.py
mcp_agent/core/request_params.py
mcp_agent/core/validation.py
mcp_agent/executor/__init__.py
mcp_agent/executor/executor.py
mcp_agent/executor/task_registry.py
mcp_agent/executor/workflow_signal.py
mcp_agent/human_input/__init__.py
mcp_agent/human_input/handler.py
mcp_agent/human_input/types.py
mcp_agent/llm/__init__.py
mcp_agent/llm/augmented_llm.py
mcp_agent/llm/augmented_llm_passthrough.py
mcp_agent/llm/augmented_llm_playback.py
mcp_agent/llm/memory.py
mcp_agent/llm/model_factory.py
mcp_agent/llm/prompt_utils.py
mcp_agent/llm/provider_key_manager.py
mcp_agent/llm/provider_types.py
mcp_agent/llm/sampling_converter.py
bee_agent-0.5.5.dist-info/METADATA
bee_agent-0.5.5.dist-info/WHEEL
bee_agent-0.5.5.dist-info/entry_points.txt
bee_agent-0.5.5.dist-info/licenses/LICENSE
bee_agent-0.5.5.dist-info/RECORD
